multilint/__init__.py
multilint/__main__.py
multilint-5.0.1.dist-info/LICENSE
multilint-5.0.1.dist-info/METADATA
multilint-5.0.1.dist-info/WHEEL
multilint-5.0.1.dist-info/entry_points.txt
multilint-5.0.1.dist-info/top_level.txt
multilint-5.0.1.dist-info/RECORD
