Metadata-Version: 2.1
Name: multilint
Version: 5.0.1
Summary: Run multiple python linters easily
Home-page: https://github.com/adamchainz/multilint
Author: Adam Johnson
Author-email: me@adamj.eu
License: ISC license
Project-URL: Changelog, https://github.com/adamchainz/multilint/blob/master/HISTORY.rst
Project-URL: Twitter, https://twitter.com/adamchainz
Keywords: lint,flake8,pep8,pycodestyle,codestyle,mccabe,setup.py
Platform: UNKNOWN
Classifier: Development Status :: 7 - Inactive
Classifier: Intended Audience :: Developers
Classifier: License :: OSI Approved :: ISC License (ISCL)
Classifier: Natural Language :: English
Classifier: Programming Language :: Python :: 3
Classifier: Programming Language :: Python :: 3.5
Classifier: Programming Language :: Python :: 3.6
Classifier: Programming Language :: Python :: 3.7
Classifier: Programming Language :: Python :: 3.8
Classifier: Programming Language :: Python :: 3.9
Requires-Python: >=3.5
